[
    {
        "name": "Teses medicas",
        "url": "https://museudehistoriadopiaui.ufpi.edu.br/acervo/documentos-acad\u00eamicos-e-cient\u00edficos/teses-medicas",
        "content": [
            {
                "title": "Tese m\u00e9dica de Manoel Affonso Fereira (1901)\u00a0",
                "drive_url": "https://drive.google.com/uc?id=1Dj8ovC1bzHMVrdy9fAUDyk-xu5wsohkc&export=download"
            },
            {
                "title": "Tese de H. Portella Parentes (1906)",
                "drive_url": "https://drive.google.com/uc?id=1R2l7jykw1FarhyJAxVzg_f4yT0OObe7s&export=download"
            },
            {
                "title": "Tese de Dr. Jo\u00e3o Virg\u00edlio dos Santos (1907)",
                "drive_url": "https://drive.google.com/uc?id=1z80q6JWP8m6vP01Br2XvJOLJo6Aog9QC&export=download"
            },
            {
                "title": "Tese de Antenor Martins Neiva (1926).",
                "drive_url": "https://drive.google.com/uc?id=1cODGveWH4W3ajxq3xac3XvvIVPUkaRU9&export=download"
            },
            {
                "title": "Tese de Luiz Brand\u00e3o Filho (1926)",
                "drive_url": "https://drive.google.com/uc?id=1e-arkmAsW_NWDKQNodpBQgwzkSvqydyN&export=download"
            },
            {
                "title": "Tese de Dr. Jo\u00e3o Em\u00edlio Falc\u00e3o Costa de 1927",
                "drive_url": "https://drive.google.com/uc?id=1CXzEi360PiDwCzvxu3iqDeMdgqcS9uC6&export=download"
            },
            {
                "title": "Tese do Dr. Anf\u00edsio Lob\u00e3o Veras Filho (1917)",
                "drive_url": "https://drive.google.com/uc?id=1yAboYN492d8IKoiyBDdMqztvCf7ajiDx&export=download"
            },
            {
                "title": "Tese do Dr. Raimundo Odorico Teixeira (1919)",
                "drive_url": "https://drive.google.com/uc?id=1e8vrN8QFRiZTbs5nBTViQG_ZShH9WUWM&export=download"
            },
            {
                "title": "Tese de Dr. Oscar Castello Branco Clark (1919)",
                "drive_url": "https://drive.google.com/uc?id=1yf10cCKLWqAVzdkWPcv2e35PvaNvF4pl&export=download"
            },
            {
                "title": "Tese de Dr. Osiris Marques da Fonseca (1924)",
                "drive_url": "https://drive.google.com/uc?id=1EJMtjQtE7M6eG96rXpNLmVXkVr1CQLNk&export=download"
            },
            {
                "title": "Disserta\u00e7\u00e3o de Fernando Ribeiro Gon\u00e7alves (1925)",
                "drive_url": "https://drive.google.com/uc?id=1j2iLlyKKMohlvkAhQpv8ocrHjis6ZbLq&export=download"
            },
            {
                "title": "Tese de Luiz Quaresma de Mello (1925)",
                "drive_url": "https://drive.google.com/uc?id=1ZjbwcM-bhh_ldTMQx6W3TniXcbgnPj9i&export=download"
            },
            {
                "title": "Tese do m\u00e9dico Deolindo Augusto de Nunes Couto (1926)",
                "drive_url": "https://drive.google.com/uc?id=1Wr_LqmJF26YfebeFRpfoBNvNXPHFXnDP&export=download"
            },
            {
                "title": "Tese de M\u00e1rio Theodomiro de Carvalho (1926)",
                "drive_url": "https://drive.google.com/uc?id=1JTdUPAhqLahp_1CVae5oezt8aGziHZac&export=download"
            },
            {
                "title": "Tese de Os\u00e9as Gon\u00e7alves de Sampaio (1927)",
                "drive_url": "https://drive.google.com/uc?id=1AFh8ODlb4E7GCHOEMIXep9kt0F_wfmnR&export=download"
            },
            {
                "title": "Tese de Francisco das Chagas Machado Lopes (1936)",
                "drive_url": "https://drive.google.com/uc?id=1FZtWaCz5zGJeuD2BVF7g6MTzd0Co6VtG&export=download"
            },
            {
                "title": "Teses m\u00e9dicas de Cl\u00e1udio Ferreira (1945), de Tomaz Ar\u00eaa Leal Filho (1946), de Aurora Maria Ribeiro Soares (1946) e de Francisco das Chagas Machado Lopes (1947)",
                "drive_url": "https://drive.google.com/uc?id=1OCVlqszAkuybh1oUJil5IeVD-KFQEMNI&export=download"
            },
            {
                "title": "Teses m\u00e9dicas de James Azevedo (1947), Antilhon Ribeiro Soares, Helena Rocha de Greslan (1945), Rog\u00e9rio de Castro Mattos (1945) e Lourival Parente (1945)",
                "drive_url": "https://drive.google.com/uc?id=1tw_p2LEbc0_7QCjH8k2q7Sblg7Q_m2Tc&export=download"
            }
        ]
    },
    {
        "name": "Faculdade de Direito do Piau\u00ed",
        "url": "https://museudehistoriadopiaui.ufpi.edu.br/acervo/documentos-acad\u00eamicos-e-cient\u00edficos/faculdade-de-direito-do-piau\u00ed",
        "content": [
            {
                "title": "Programa de ensino introdu\u00e7\u00e3o \u00e0 Sciencia do Direito",
                "drive_url": "https://drive.google.com/uc?id=1Ztsky22B5hCn_cEvcMHxmhyzWW58BurS&export=download"
            },
            {
                "title": "Estatuto da Ordem dos Bachar\u00e9is em Direito do Piauhy\u00a0",
                "drive_url": "https://drive.google.com/uc?id=1F-4H57L7r8hoxfvrdihqsPqhSjwRkU5Q&export=download"
            },
            {
                "title": "Estatutos da Faculdade de Direito do Piauhy",
                "drive_url": "https://drive.google.com/uc?id=1a1GIlEZRx2fD8eATVROmhaM699zfk_Ld&export=download"
            },
            {
                "title": "Regulamento da Faculdade de Direito",
                "drive_url": "https://drive.google.com/uc?id=1MLyHxxX6Sp-zIkraSDr-9CSwQf-qcqmt&export=download"
            }
        ]
    },
    {
        "name": "Faculdade de Farmacia",
        "url": "https://museudehistoriadopiaui.ufpi.edu.br/acervo/documentos-acad\u00eamicos-e-cient\u00edficos/faculdade-de-farm\u00e1cia-e-odontologia",
        "content": [
            {
                "title": "Estatutos da Faculdade de Farm\u00e1cia e Odontologia (1953)",
                "drive_url": "https://drive.google.com/uc?id=112EiSv7EW3uT_9FQXQSU6uoUv94EvTBV&export=download"
            }
        ]
    },
    {
        "name": "Documentos sobre o Meduna",
        "url": "https://museudehistoriadopiaui.ufpi.edu.br/acervo/documentos-acad\u00eamicos-e-cient\u00edficos/meduna",
        "content": [
            {
                "title": "Estatuto do Sanat\u00f3rio Meduna S.A. de 1967",
                "drive_url": "https://drive.google.com/uc?id=1MgvIy4SHwPiLGmTWcpRnHzVkvjEOUHSS&export=download"
            },
            {
                "title": "Carta a meus filhos - Cliedenor de Freitas Santos (1954)",
                "drive_url": "https://drive.google.com/uc?id=1i5Bl17t_i4KtlQi3lhvve_T0j6dxw_3c&export=download"
            }
        ]
    }
]